mlsteam/__init__.py
mlsteam/api.py
mlsteam/auth.py
mlsteam/checkpoint.py
mlsteam/cli.py
mlsteam/consumer.py
mlsteam/container.py
mlsteam/dataset.py
mlsteam/ds.py
mlsteam/envs.py
mlsteam/exceptions.py
mlsteam/info.py
mlsteam/job.py
mlsteam/keras.py
mlsteam/metrics.py
mlsteam/model.py
mlsteam/project.py
mlsteam/service.py
mlsteam/stparams.py
mlsteam/track.py
mlsteam/utils.py
mlsteam/version.py
mlsteam/work.py
mlsteam/api_clients/__init__.py
mlsteam/api_clients/credential.py
mlsteam/batch_processor/__init__.py
mlsteam_client-0.5.0.data/data/bin/mc
tests/__init__.py
tests/config.py
tests/test_api.py
tests/test_basic.py
tests/test_negative_api.py
tests/test_negative_basic.py
tests/test_track.py
mlsteam_client-0.5.0.dist-info/LICENSE
mlsteam_client-0.5.0.dist-info/METADATA
mlsteam_client-0.5.0.dist-info/WHEEL
mlsteam_client-0.5.0.dist-info/entry_points.txt
mlsteam_client-0.5.0.dist-info/top_level.txt
mlsteam_client-0.5.0.dist-info/RECORD
