Metadata-Version: 2.1
Name: mlsteam-client
Version: 0.5.0
Summary: MLSteam Client
Home-page: https://myelintek.com
Author: MyelinTek inc.
Author-email: simon@myelintek.com
License: MIT
Keywords: Deep Learning Tracking
Platform: UNKNOWN
Classifier: Development Status :: 3 - Alpha
Classifier: Environment :: Console
Classifier: Intended Audience :: Developers
Classifier: Intended Audience :: Science/Research
Classifier: License :: OSI Approved :: MIT License
Classifier: Natural Language :: English
Classifier: Operating System :: POSIX :: Linux
Classifier: Programming Language :: Python :: 3
Classifier: Programming Language :: Python :: 3.6
Classifier: Programming Language :: Python :: 3.7
Classifier: Programming Language :: Python :: 3.8
Classifier: Programming Language :: Python :: 3.9
Classifier: Topic :: Software Development :: Libraries :: Python Modules
Classifier: Programming Language :: Python :: Implementation :: CPython
Classifier: Topic :: Scientific/Engineering :: Artificial Intelligence
Requires-Python: >=3.6.0
Requires-Dist: bravado (==11.0.2)
Requires-Dist: click (==8.0.3)
Requires-Dist: jsonschema (<4)
Requires-Dist: pyyaml (>=5.3.1)
Requires-Dist: requests (==2.25.1)
